opticomlib/__init__.py
opticomlib/devices.py
opticomlib/lab.py
opticomlib/ook.py
opticomlib/ppm.py
opticomlib/typing.py
opticomlib/utils.py
opticomlib-1.5.11.dist-info/licenses/LICENSE.md
opticomlib-1.5.11.dist-info/METADATA
opticomlib-1.5.11.dist-info/WHEEL
opticomlib-1.5.11.dist-info/top_level.txt
opticomlib-1.5.11.dist-info/RECORD
