Metadata-Version: 2.4
Name: opticomlib
Version: 1.5.11
Summary: Python package for optical communication systems.
Home-page: https://github.com/armando-palacio/opticomlib.git
Maintainer: Armando P. Romeu
Maintainer-email: armandopr3009@gmail.com
License: MIT
Classifier: Development Status :: 4 - Beta
Classifier: Intended Audience :: Science/Research
Classifier: Intended Audience :: Telecommunications Industry
Classifier: Programming Language :: Python :: 3
Requires-Python: >=3.10
License-File: LICENSE.md
Requires-Dist: scipy==1.12.0
Requires-Dist: numpy==1.26.4
Requires-Dist: matplotlib==3.10.1
Requires-Dist: scikit-learn==1.6.1
Requires-Dist: tqdm==4.67.1
Requires-Dist: pympler==1.1
Requires-Dist: pyvisa==1.14.1
Provides-Extra: opticomlib
Requires-Dist: scipy==1.12.0; extra == "opticomlib"
Requires-Dist: numpy==1.26.4; extra == "opticomlib"
Requires-Dist: matplotlib==3.10.1; extra == "opticomlib"
Requires-Dist: scikit-learn==1.6.1; extra == "opticomlib"
Requires-Dist: tqdm==4.67.1; extra == "opticomlib"
Requires-Dist: pympler==1.1; extra == "opticomlib"
Requires-Dist: pyvisa==1.14.1; extra == "opticomlib"
Dynamic: classifier
Dynamic: description
Dynamic: description-content-type
Dynamic: home-page
Dynamic: license
Dynamic: license-file
Dynamic: maintainer
Dynamic: maintainer-email
Dynamic: provides-extra
Dynamic: requires-dist
Dynamic: requires-python
Dynamic: summary
